.coveragerc
.gitignore
.readthedocs.yml
AUTHORS.rst
CHANGELOG.rst
LICENSE
README.md
pyproject.toml
requirements.txt
setup.cfg
setup.py
tox.ini
docs/Makefile
docs/authors.rst
docs/changelog.rst
docs/clustering.rst
docs/conf.py
docs/features.rst
docs/group_features.rst
docs/index.rst
docs/license.rst
docs/network.rst
docs/quick_start.rst
docs/readme.rst
docs/requirements.txt
docs/spatial_analysis.rst
docs/_static/.gitignore
docs/examples/01_data_cleaning.ipynb
docs/examples/02_extract_features.ipynb
docs/examples/03_group_features.ipynb
docs/examples/04_spatial_analysis.ipynb
docs/examples/05_network_analysis.ipynb
docs/examples/06_clustering.ipynb
docs/examples/07_movebank.ipynb
docs/examples/datasets/Mangabey_monkeys_in_Uganda.csv
docs/examples/datasets/fish-4.geojson
docs/examples/datasets/fish-5-cleaned.csv
docs/examples/datasets/fish-5-features.csv
docs/examples/datasets/fish-5.csv
docs/examples/datasets/fish-5.geojson
docs/examples/datasets/fish-5.xlsx
docs/examples/datasets/fish-6.csv
docs/examples/datasets/geo.csv
examples/01_data_cleaning.ipynb
examples/02_extract_features.ipynb
examples/03_group_features.ipynb
examples/04_spatial_analysis.ipynb
examples/05_network_analysis.ipynb
examples/06_clustering.ipynb
examples/07_movebank.ipynb
examples/datasets/Mangabey_monkeys_in_Uganda.csv
examples/datasets/fish-4.geojson
examples/datasets/fish-5-cleaned.csv
examples/datasets/fish-5-features.csv
examples/datasets/fish-5.csv
examples/datasets/fish-5.geojson
examples/datasets/fish-5.xlsx
examples/datasets/fish-6.csv
examples/datasets/geo.csv
media/clustering.png
media/movebank.png
media/movement.png
media/mover.gif
media/network.png
media/voronoi.png
src/movekit/__init__.py
src/movekit/clustering.py
src/movekit/feature_extraction.py
src/movekit/io.py
src/movekit/network.py
src/movekit/plot.py
src/movekit/preprocess.py
src/movekit/utils.py
src/movekit.egg-info/PKG-INFO
src/movekit.egg-info/SOURCES.txt
src/movekit.egg-info/dependency_links.txt
src/movekit.egg-info/not-zip-safe
src/movekit.egg-info/requires.txt
src/movekit.egg-info/top_level.txt
src/movekit/.ipynb_checkpoints/__init__-checkpoint.py
src/movekit/.ipynb_checkpoints/clustering-checkpoint.py
