Metadata-Version: 2.1
Name: movekit
Version: 0.1.25
Summary: Simple and effective tools for the analysis of movement data
Home-page: https://github.com/dbvis-ukon/movekit
Author: Lukas Weixkler, Arjun Majumdar, Eren Cakmak, Jolle Jolles
Author-email: lukas.weixler@uni-konstanz.de, arjun.majumdar@uni-konstanz.de, eren.cakmak@uni-konstanz.de, j.w.jolles@gmail.com
License: License :: OSI Approved :: GNU General Public License v3 (GPLv3)
Project-URL: Documentation, https://pyscaffold.org/
Platform: any
Classifier: Development Status :: 2 - Pre-Alpha
Classifier: Intended Audience :: Science/Research
Classifier: Intended Audience :: Developers
Classifier: License :: OSI Approved :: GNU General Public License v3 (GPLv3)
Classifier: Programming Language :: Python
Classifier: Programming Language :: Python :: 3
Classifier: Programming Language :: Python :: 3.5
Classifier: Programming Language :: Python :: 3.6
Classifier: Programming Language :: Python :: 3.7
Classifier: Programming Language :: Python :: 3.8
Classifier: Programming Language :: Python :: 3.9
Classifier: Topic :: Software Development
Classifier: Topic :: Scientific/Engineering
Classifier: Operating System :: Microsoft :: Windows
Classifier: Operating System :: Unix
Classifier: Operating System :: MacOS
Requires-Python: <3.10,>=3.5
Provides-Extra: testing
License-File: LICENSE
License-File: AUTHORS.rst
